geowanhee/__init__.py
geowanhee/common.py
geowanhee/geowanhee.py
geowanhee-0.0.1.dist-info/LICENSE
geowanhee-0.0.1.dist-info/METADATA
geowanhee-0.0.1.dist-info/WHEEL
geowanhee-0.0.1.dist-info/entry_points.txt
geowanhee-0.0.1.dist-info/top_level.txt
geowanhee-0.0.1.dist-info/RECORD
