Metadata-Version: 2.1
Name: geowanhee
Version: 0.0.1
Summary: a python package for wanhee's geo510
Author-email: Wanhee Kim <wkim15@vols.utk.edu>
License: MIT License
Project-URL: Homepage, https://github.com/whkim15/geowanhee
Keywords: geowanhee
Classifier: Intended Audience :: Developers
Classifier: License :: OSI Approved :: MIT License
Classifier: Natural Language :: English
Classifier: Programming Language :: Python :: 3.8
Classifier: Programming Language :: Python :: 3.9
Classifier: Programming Language :: Python :: 3.10
Classifier: Programming Language :: Python :: 3.11
Classifier: Programming Language :: Python :: 3.12
Requires-Python: >=3.8
License-File: LICENSE
Requires-Dist: numpy
Provides-Extra: all
Requires-Dist: geowanhee[extra] ; extra == 'all'
Provides-Extra: extra
Requires-Dist: pandas ; extra == 'extra'
